Workbook

Sheet 统计
A1: 实测统计（自动计算，不要手改）
A2: 分类 | B2: 指标 | C2: 数值 | D2: 占答偏比 | E2: 说明
A3: 总览 | B3: 已完成判定轮数 | C3: =COUNTIF(实测记录!$E$4:$E$33,"答对")+COUNTIF(实测记录!$E$4:$E$33,"答偏") -> 30 | E3: 已判定「答对 / 答偏」的轮数
A4: 总览 | B4: 答对轮数 | C4: =COUNTIF(实测记录!$E$4:$E$33,"答对") -> 21 | E4: 结果列选“答对”的条数
A5: 总览 | B5: 答偏轮数 | C5: =COUNTIF(实测记录!$E$4:$E$33,"答偏") -> 9 | E5: 结果列选“答偏”的条数
A6: 总览 | B6: 答偏率 | C6: =IF(OR(C3="",C3=0),"",C5/C3) -> 0.3 | E6: 答偏轮数 ÷ 实测总轮数
A7: 归因 | B7: 语料未覆盖（答非所问） | C7: =COUNTIF(实测记录!$F$4:$F$33,"语料未覆盖") -> 1 | D7: =IF(OR($C$5="",$C$5=0),"",C7/$C$5) -> 0.11111111 | E7: AI 答得通顺，但不是你问的那件事
A8: 归因 | B8: 知识库缺失（答不上来） | C8: =COUNTIF(实测记录!$F$4:$F$33,"知识库缺失") -> 1 | D8: =IF(OR($C$5="",$C$5=0),"",C8/$C$5) -> 0.11111111 | E8: AI 直接说不知道 / 让找人工
A9: 归因 | B9: 意图识别错（理解偏了） | C9: =COUNTIF(实测记录!$F$4:$F$33,"意图识别错") -> 7 | D9: =IF(OR($C$5="",$C$5=0),"",C9/$C$5) -> 0.77777778 | E9: AI 理解成了另一件事，方向错了
A10: 场景 | B10: 退款 · 答偏数 | C10: =COUNTIFS(实测记录!$B$4:$B$33,"退款",实测记录!$E$4:$E$33,"答偏") -> 3 | D10: =IF(OR($C$5="",$C$5=0),"",C10/$C$5) -> 0.33333333 | E10: 退款场景里答偏了几轮
A11: 场景 | B11: 改单 · 答偏数 | C11: =COUNTIFS(实测记录!$B$4:$B$33,"改单",实测记录!$E$4:$E$33,"答偏") -> 1 | D11: =IF(OR($C$5="",$C$5=0),"",C11/$C$5) -> 0.11111111 | E11: 改单场景里答偏了几轮
A12: 场景 | B12: 物流 · 答偏数 | C12: =COUNTIFS(实测记录!$B$4:$B$33,"物流",实测记录!$E$4:$E$33,"答偏") -> 4 | D12: =IF(OR($C$5="",$C$5=0),"",C12/$C$5) -> 0.44444444 | E12: 物流场景里答偏了几轮
A13: 场景 | B13: 催件 · 答偏数 | C13: =COUNTIFS(实测记录!$B$4:$B$33,"催件",实测记录!$E$4:$E$33,"答偏") -> 1 | D13: =IF(OR($C$5="",$C$5=0),"",C13/$C$5) -> 0.11111111 | E13: 催件场景里答偏了几轮

Sheet 实测记录
A1: AI 客服应答实测记录
A2: 被测平台 | B2: 支付宝「我的客服」（蚂蚁智服） | C2: 测试日期 | D2: 2026-09-29
A3: 序号 | B3: 场景 | C3: 我的提问 | D3: AI 的回答（摘要） | E3: 结果 | F3: 错因分类 | G3: 我的判断与更好的答法
A4: =ROW()-3 -> 1 | B4: 退款 | C4: 转账转错了能退回来吗 | D4: 先让核对最近转账记录、选一笔订单，未直接回答转错能否退回。 | E4: 答偏 | F4: 意图识别错 | G4: 规则型问题被当成个人数据查询。应先给结论：对方未收款可协商退回，已收款需自行沟通或走客服申诉，再提查订单。交叉验证：同一知识换个问法（第2题）就答对，说明知识有、路由错。
A5: =ROW()-3 -> 2 | B5: 退款 | C5: 转账失败的钱多久退回 | D5: 说明转账失败资金会原路退回、一般实时到账，超时未到会原路返回，并给出查转账记录路径。 | E5: 答对 | F5: 不适用 | G5: 结论在前、时间口径明确。与第1题同知识域，换问法即答对，反证第1题属路由问题而非知识缺失。
A6: =ROW()-3 -> 3 | B6: 退款 | C6: 花呗退款是退到哪里 | D6: 按支付方式分支说明：花呗支付退回花呗额度，余额支付退回余额，银行卡支付退回银行卡。 | E6: 答对 | F6: 不适用 | G6: 典型「条件→结果」分支结构，本轮正面样本之一。
A7: =ROW()-3 -> 4 | B7: 退款 | C7: 余额宝转出要多久到账 | D7: 分两档给时长：快速转出当日到账（日限1万元）、普通转出T+1个交易日。 | E7: 答对 | F7: 不适用 | G7: 分类分档给时长，口径清晰可直接采信。
A8: =ROW()-3 -> 5 | B8: 退款 | C8: 自动续费扣的钱能退吗 | D8: 未回答能否退款，转而展示如何关闭自动续费、查询扣款记录。 | E8: 答偏 | F8: 意图识别错 | G8: 问「能不能退」，答「怎么关」——把诉求理解成关闭续费。应先给结论（已扣费用原则上不退，可与商家协商或申诉），再附关闭路径。
A9: =ROW()-3 -> 6 | B9: 退款 | C9: 退款显示成功但没收到怎么办 | D9: 按到账渠道说明延迟原因，给出核对账户流水与联系客服的排查路径。 | E9: 答对 | F9: 不适用 | G9: 给了排查路径+结论，可用。
A10: =ROW()-3 -> 7 | B10: 退款 | C10: 提现要收手续费吗 | D10: 说明余额提现免手续费及限额规则，并区分不同资金来源的口径。 | E10: 答对 | F10: 不适用 | G10: 规则类问题直接作答，结论明确。
A11: =ROW()-3 -> 8 | B11: 退款 | C11: 转账到银行卡多久能到 | D11: 未直接给到账时长，导流到查询具体转账记录的订单详情。 | E11: 答偏 | F11: 意图识别错 | G11: 与第1题同型：规则问句被导向个人订单查询。应先给分档时长（2小时/次日等）再提查订单。规律：问句一旦含「我账户里的动作」，就容易触发查询分支，属路由层系统性偏差。
A12: =ROW()-3 -> 9 | B12: 改单 | C12: 怎么修改绑定的手机号 | D12: 给出「设置→账号与安全→手机号」的完整路径，并提示需原手机号验证。 | E12: 答对 | F12: 不适用 | G12: 路径完整，可直接照做。
A13: =ROW()-3 -> 10 | B13: 改单 | C13: 实名信息认证错了能改吗 | D13: 说明实名信息原则上不可自行修改，需走人工/申诉通道并提供材料。 | E13: 答对 | F13: 不适用 | G13: 结论明确，并给了替代路径。
A14: =ROW()-3 -> 11 | B14: 改单 | C14: 怎么更换绑定的银行卡 | D14: 给出银行卡管理→解绑/添加的操作路径与注意事项。 | E14: 答对 | F14: 不适用 | G14: 路径完整。
A15: =ROW()-3 -> 12 | B15: 改单 | C15: 付款方式能调整顺序吗 | D15: 说明可在支付设置里调整扣款顺序，并给出设置路径。 | E15: 答对 | F15: 不适用 | G15: 路径完整。
... A33: =ROW()-3 -> 30 | B33: 催件 | C33: 举报之后多久会有处理结果 | D33: 明确24小时内完成审核，通过【服务提醒】反馈结果；可在【支付宝举报中心】查记录与结果；不认可可补充凭证申请重审。 | E33: 答对 | F33: 不适用 | G33: 时限+反馈方式+查询入口+申诉兜底，四要素齐全，可作时效类问题的正面模板。

Sheet 操作说明
A1: AI 客服应答实测 · 操作说明
A3: 一、开测前
A4: 1 | B4: 打开支付宝 App → 我的 → 我的客服，进对话框后直接打字提问，不要点它推的常见问题。要用有业务知识库的那种，不要拿通用聊天助手凑。
A5: 2 | B5: 在「实测记录」表顶部填上被测平台（支付宝「我的客服」）和测试日期。
A6: 二、怎么测（约 2 小时）
A7: 3 | B7: 30 个问题已经预填在「实测记录」里，都是问支付和账户规则的，不需要交易单号，直接复制粘贴到客服输入框就能问。
A8: 4 | B8: 每问一句，就把 AI 的回复复制到「AI 的回答（摘要）」列，太长截前两三句。
A9: 5 | B9: 判断这轮是「答对」还是「答偏」，在「结果」列下拉选。判断标准：能不能解决你问的那件事。
A10: 6 | B10: 答偏的，在「错因分类」列选三类之一，在最后一列写下你自己的判断和更好的答法。
A11: 三、三类错因怎么区分
A12: 语料未覆盖 | B12: AI 答得通顺、态度也好，但答的不是你问的那件事。它没见过这种问法的语料。
A13: 知识库缺失 | B13: AI 明说“这个我不清楚”“建议联系人工客服”。知识库里压根没有这条内容。
A14: 意图识别错 | B14: AI 把你的问题理解成了另一件事，答得很认真，但方向一开始就错了。
A15: 四、做完之后
A16: 7 | B16: 「统计」表会自动算出：已完成判定轮数、答偏例数、答偏率、三类归因各多少、哪类场景最容易错。不用自己算。
A17: 8 | B17: 把统计出来的数字填进简历里那几个红色【填】。
A18: 9 | B18: 截图或录屏留证。面试里说“我实测了 30 轮”，得拿得出东西。
A19: 五、注意
A20: 10 | B20: 答偏率不用美化。30 轮答偏 9 轮就写 9 轮（本次实测结果）。AI 面会顺着你简历上的数字追问，编的数字一问就穿帮。
A21: 11 | B21: 同一句话不要问两遍，重复提问不算新样本。
A22: 12 | B22: 场景名统一用「退款 / 改单 / 物流 / 催件」这四个词，不然统计表的公式对不上。在支付宝里对应：转账与退款到账→退款、改绑定与改设置→改单、账户状态与审核进度→物流、工单催办与投诉→催件。
A23: 13 | B23: 最后一列别空着。面试官问“你怎么知道是意图识别错”，答案就在你自己写的判断里。
A24: 14 | B24: 如果 AI 一句不答就把你转人工，这轮记「知识库缺失」，在最后一列注明“直接转人工”。
A25: 六、这些问题为什么不用交易单号
A26: 15 | B26: 这 30 条问的都是通用规则——多久到账、能不能改、要哪些材料。客服答这些不用看你的账单，所以可以直接在客服输入框里问，不用先交易、也不用报流水号。
A27: 16 | B27: 万一某一条客服非要交易单号，直接跳过，在最后一列写“要单号，未答”。别为了一两条去折腾，30 条里有 25 条以上都是能直接答的。
A28: 七、实测结论（2026-09-29 已完成 30 轮）
A29: 17 | B29: 总成绩：30 轮答对 21、答偏 9，答偏率 30.0%。
A30: 18 | B30: 场景差异：物流 57.1%（最高，7 轮偏 4）＞ 退款 37.5%（8 轮偏 3）＞ 催件 14.3%（7 轮偏 1）＞ 改单 12.5%（8 轮偏 1）。
A31: 19 | B31: 错因分布：意图识别错 7、语料未覆盖 1、知识库缺失 1。七成集中在「把规则问句误导向个人数据查询」这一个路由偏差上。
A32: 20 | B32: 核心结论：知识层覆盖充足（同一知识换个问法就能答对，交叉验证 3 次）；瓶颈在应答编排层——结论位置不固定、规则与数据先后不统一、失败时的澄清方式不一致。
A33: 21 | B33: 改进建议：把高频动作类问句统一改写成「条件 → 结果」分支结构（它自己在第3、4、14、28、30 题已经是这种结构，证明能力具备，只是没铺满）。
A34: 22 | B34: 正面样本：第 3、4、14、28、30 题。反面样本：第 1、8、18、19、22、23 题（同一路由偏差）。可直接用于面试举证。
